cronpie/__init__.py
cronpie/cronpie.py
cronpie-0.2.0.dist-info/METADATA
cronpie-0.2.0.dist-info/WHEEL
cronpie-0.2.0.dist-info/top_level.txt
cronpie-0.2.0.dist-info/RECORD
